test/__init__.py
test/test_access201_response.py
test/test_access_request.py
test/test_account_api.py
test/test_add_frontend_grant_request.py
test/test_add_organization_member_request.py
test/test_admin_api.py
test/test_agent_api.py
test/test_auth_user.py
test/test_change_password_request.py
test/test_client_version_check_request.py
test/test_configuration.py
test/test_create_frontend201_response.py
test/test_create_frontend_request.py
test/test_create_identity201_response.py
test/test_create_identity_request.py
test/test_create_organization201_response.py
test/test_create_organization_request.py
test/test_delete_identity_request.py
test/test_disable_request.py
test/test_enable_request.py
test/test_enroll200_response.py
test/test_enroll_request.py
test/test_environment.py
test/test_environment_and_resources.py
test/test_environment_api.py
test/test_frontend.py
test/test_get_sparklines200_response.py
test/test_get_sparklines_request.py
test/test_invite_request.py
test/test_invite_token_generate_request.py
test/test_list_frontends200_response_inner.py
test/test_list_memberships200_response.py
test/test_list_memberships200_response_memberships_inner.py
test/test_list_organization_members200_response.py
test/test_list_organization_members200_response_members_inner.py
test/test_list_organizations200_response.py
test/test_list_organizations200_response_organizations_inner.py
test/test_list_public_frontends_for_account200_response.py
test/test_list_public_frontends_for_account200_response_public_frontends_inner.py
test/test_login_request.py
test/test_metadata_api.py
test/test_metrics.py
test/test_metrics_sample.py
test/test_overview.py
test/test_ping200_response.py
test/test_principal.py
test/test_regenerate_account_token200_response.py
test/test_regenerate_account_token_request.py
test/test_register_request.py
test/test_remote_access_request.py
test/test_remote_share200_response.py
test/test_remote_share_request.py
test/test_remote_status200_response.py
zrok-1.1.10.dist-info/METADATA
zrok-1.1.10.dist-info/WHEEL
zrok-1.1.10.dist-info/top_level.txt
zrok-1.1.10.dist-info/RECORD
